{
  "name": "postgres-customers-connector",
  "config": {
    "connector.class": "io.debezium.connector.postgresql.PostgresConnector",
    "database.hostname": "psql",
    "database.port": "5432",
    "database.user": "admin",
    "database.password": "admin123",
    "database.dbname": "sales",
    "database.server.name": "pgserver",
    "table.include.list": "sales.customers",
    "plugin.name": "pgoutput",
    "slot.name": "debezium_slot",
    "publication.name": "dbz_publication",
    "key.converter": "org.apache.kafka.connect.json.JsonConverter",
    "value.converter": "org.apache.kafka.connect.json.JsonConverter",
    "key.converter.schemas.enable": false,
    "value.converter.schemas.enable": false,
    "topic.prefix": "pgserver"
  }
}
